{
	"version": "v1",
	"config": {
		"total-time": 1800
	},
	"topology": {
		"attackers": [{
			"name": "attacker-1",
			"version": "strategy-v5",
			"config": "./config/attacker-config.toml",
			"strategy": "./strategy/strategy.json"
		}],
		"executors": [{
			"name": "execute-1",
			"version": "v1.13-base-v5"
		},
		{
			"name": "execute-2",
			"version": "v1.13-base-v5"
		},
		{
			"name": "execute-3",
			"version": "v1.13-base-v5"
		},
		{
			"name": "execute-4",
			"version": "v1.13-base-v5"
		},
		{
			"name": "execute-5",
			"version": "v1.13-base-v5"
		}
		],
		"beacons": [{
			"name": "beacon-1",
			"version": "v5.0.1-t1",
			"env": {
				"ATTACKER_SERVICE_URL": "http://172.17.0.1:12000"
			},
			"executor": "execute-1"
		},
		{
			"name": "beacon-2",
			"version": "v5.0.1-base",
			"executor": "execute-2"
		},
		{
			"name": "beacon-3",
			"version": "v5.0.1-base",
			"executor": "execute-3"
		},
		{
			"name": "beacon-4",
			"version": "v5.0.1-base",
			"executor": "execute-4"
		},
		{
			"name": "beacon-5",
			"version": "v5.0.1-base",
			"executor": "execute-5"
		}
		],
		"validators": [{
			"name": "validator-1",
			"version": "v5.0.1-t1",
			"env": {
				"ATTACKER_SERVICE_URL": "http://172.17.0.1:12000"
			},
			"beacon": "beacon-1",
			"validator_count": 85
		},
		{
			"name": "validator-2",
			"version": "v5.0.1-base",
			"beacon": "beacon-2",
			"validator_count": 51
		},
		{
			"name": "validator-3",
			"version": "v5.0.1-base",
			"beacon": "beacon-3",
			"validator_count": 51
		},
		{
			"name": "validator-4",
			"version": "v5.0.1-base",
			"beacon": "beacon-4",
			"validator_count": 51
		},
		{
			"name": "validator-5",
			"version": "v5.0.1-base",
			"beacon": "beacon-5"
		}
		]
	}
}
